setup.py
gbinom_distributions/Binomialdistribution.py
gbinom_distributions/Gaussiandistribution.py
gbinom_distributions/Generaldistribution.py
gbinom_distributions/__init__.py
gbinom_distributions.egg-info/PKG-INFO
gbinom_distributions.egg-info/SOURCES.txt
gbinom_distributions.egg-info/dependency_links.txt
gbinom_distributions.egg-info/not-zip-safe
gbinom_distributions.egg-info/top_level.txt