Metadata-Version: 1.0
Name: gbinom-distributions
Version: 1.1
Summary: Gaussian and Binomial distributions
Home-page: UNKNOWN
Author: Hamid Adesokan
Author-email: aadehamid@gmail.com
License: UNKNOWN
Platform: UNKNOWN
